{
  "date": "2015-03-20 00:00",
  "stop": {
    "id": "2_1003",
    "lat": 48.127369,
    "lon": -1.640433,
    "name": "Gallets",
    "code": 1003
  },
  "routes": [
    {
      "id": "2_0001",
      "textColor": "1A171B",
      "color": "97BF0D",
      "description": "Majeure",
      "longName": "Cesson-Sévigné (Champs Blancs) \u003c\u003e Chantepie (Rosa Parks)",
      "shortName": "1",
      "type": 3,
      "agencyId": "2"
    },
    {
      "id": "2_0804",
      "textColor": "FFFFFF",
      "color": "009C99",
      "description": "Spéciale",
      "longName": "Rennes \u003c\u003e Touche Tizon",
      "shortName": "TTZ",
      "type": 3,
      "agencyId": "2"
    }
  ],
  "stopTimes": [
    {
      "arrival": "2015-03-20 04:26",
      "departure": "2015-03-20 04:26",
      "serviceId": "2_38",
      "tripId": "2_7608",
      "routeId": "2_0804",
      "headsign": "TTZ | Touche Tizon 3"
    },
    {
      "arrival": "2015-03-20 05:28",
      "departure": "2015-03-20 05:28",
      "serviceId": "2_36",
      "tripId": "2_15683",
      "routeId": "2_0001",
      "headsign": "1 | Chantepie Rosa Parks"
    },
    {
      "arrival": "2015-03-20 06:08",
      "departure": "2015-03-20 06:08",
      "serviceId": "2_36",
      "tripId": "2_15033",
      "routeId": "2_0001",
      "headsign": "1 | Chantepie Rosa Parks"
    },
    {
      "arrival": "2015-03-20 06:28",
      "departure": "2015-03-20 06:28",
      "serviceId": "2_36",
      "tripId": "2_15693",
      "routeId": "2_0001",
      "headsign": "1 | Chantepie Rosa Parks"
    },
    {
      "arrival": "2015-03-20 06:50",
      "departure": "2015-03-20 06:50",
      "serviceId": "2_36",
      "tripId": "2_15068",
      "routeId": "2_0001",
      "headsign": "1 | Chantepie Rosa Parks"
    },
    {
      "arrival": "2015-03-20 07:04",
      "departure": "2015-03-20 07:04",
      "serviceId": "2_36",
      "tripId": "2_15743",
      "routeId": "2_0001",
      "headsign": "1 | Chantepie Rosa Parks"
    },
    {
      "arrival": "2015-03-20 07:13",
      "departure": "2015-03-20 07:13",
      "serviceId": "2_36",
      "tripId": "2_15508",
      "routeId": "2_0001",
      "headsign": "1 | Chantepie Rosa Parks"
    },
    {
      "arrival": "2015-03-20 07:21",
      "departure": "2015-03-20 07:21",
      "serviceId": "2_36",
      "tripId": "2_15698",
      "routeId": "2_0001",
      "headsign": "1 | Chantepie Rosa Parks"
    },
    {
      "arrival": "2015-03-20 07:27",
      "departure": "2015-03-20 07:27",
      "serviceId": "2_36",
      "tripId": "2_15863",
      "routeId": "2_0001",
      "headsign": "1 | Chantepie Rosa Parks"
    },
    {
      "arrival": "2015-03-20 07:35",
      "departure": "2015-03-20 07:35",
      "serviceId": "2_36",
      "tripId": "2_15718",
      "routeId": "2_0001",
      "headsign": "1 | Chantepie Rosa Parks"
    },
    {
      "arrival": "2015-03-20 07:42",
      "departure": "2015-03-20 07:42",
      "serviceId": "2_36",
      "tripId": "2_15628",
      "routeId": "2_0001",
      "headsign": "1 | Chantepie Rosa Parks"
    },
    {
      "arrival": "2015-03-20 07:50",
      "departure": "2015-03-20 07:50",
      "serviceId": "2_36",
      "tripId": "2_15648",
      "routeId": "2_0001",
      "headsign": "1 | Chantepie Rosa Parks"
    },
    {
      "arrival": "2015-03-20 07:58",
      "departure": "2015-03-20 07:58",
      "serviceId": "2_36",
      "tripId": "2_15653",
      "routeId": "2_0001",
      "headsign": "1 | Chantepie Rosa Parks"
    },
    {
      "arrival": "2015-03-20 08:06",
      "departure": "2015-03-20 08:06",
      "serviceId": "2_36",
      "tripId": "2_15668",
      "routeId": "2_0001",
      "headsign": "1 | Chantepie Rosa Parks"
    },
    {
      "arrival": "2015-03-20 08:14",
      "departure": "2015-03-20 08:14",
      "serviceId": "2_36",
      "tripId": "2_15088",
      "routeId": "2_0001",
      "headsign": "1 | Chantepie Rosa Parks"
    },
    {
      "arrival": "2015-03-20 08:22",
      "departure": "2015-03-20 08:22",
      "serviceId": "2_36",
      "tripId": "2_15108",
      "routeId": "2_0001",
      "headsign": "1 | Chantepie Rosa Parks"
    },
    {
      "arrival": "2015-03-20 08:30",
      "departure": "2015-03-20 08:30",
      "serviceId": "2_36",
      "tripId": "2_15578",
      "routeId": "2_0001",
      "headsign": "1 | Chantepie Rosa Parks"
    },
    {
      "arrival": "2015-03-20 08:39",
      "departure": "2015-03-20 08:39",
      "serviceId": "2_36",
      "tripId": "2_15003",
      "routeId": "2_0001",
      "headsign": "1 | Chantepie Rosa Parks"
    },
    {
      "arrival": "2015-03-20 08:47",
      "departure": "2015-03-20 08:47",
      "serviceId": "2_36",
      "tripId": "2_15703",
      "routeId": "2_0001",
      "headsign": "1 | Chantepie Rosa Parks"
    },
    {
      "arrival": "2015-03-20 08:56",
      "departure": "2015-03-20 08:56",
      "serviceId": "2_36",
      "tripId": "2_15073",
      "routeId": "2_0001",
      "headsign": "1 | Chantepie Rosa Parks"
    },
    {
      "arrival": "2015-03-20 09:07",
      "departure": "2015-03-20 09:07",
      "serviceId": "2_36",
      "tripId": "2_15103",
      "routeId": "2_0001",
      "headsign": "1 | Chantepie Rosa Parks"
    },
    {
      "arrival": "2015-03-20 09:17",
      "departure": "2015-03-20 09:17",
      "serviceId": "2_36",
      "tripId": "2_15118",
      "routeId": "2_0001",
      "headsign": "1 | Chantepie Rosa Parks"
    },
    {
      "arrival": "2015-03-20 09:27",
      "departure": "2015-03-20 09:27",
      "serviceId": "2_36",
      "tripId": "2_15113",
      "routeId": "2_0001",
      "headsign": "1 | Chantepie Rosa Parks"
    },
    {
      "arrival": "2015-03-20 09:37",
      "departure": "2015-03-20 09:37",
      "serviceId": "2_36",
      "tripId": "2_15128",
      "routeId": "2_0001",
      "headsign": "1 | Chantepie Rosa Parks"
    },
    {
      "arrival": "2015-03-20 09:47",
      "departure": "2015-03-20 09:47",
      "serviceId": "2_36",
      "tripId": "2_15123",
      "routeId": "2_0001",
      "headsign": "1 | Chantepie Rosa Parks"
    },
    {
      "arrival": "2015-03-20 09:57",
      "departure": "2015-03-20 09:57",
      "serviceId": "2_36",
      "tripId": "2_15138",
      "routeId": "2_0001",
      "headsign": "1 | Chantepie Rosa Parks"
    },
    {
      "arrival": "2015-03-20 10:07",
      "departure": "2015-03-20 10:07",
      "serviceId": "2_36",
      "tripId": "2_15133",
      "routeId": "2_0001",
      "headsign": "1 | Chantepie Rosa Parks"
    },
    {
      "arrival": "2015-03-20 10:17",
      "departure": "2015-03-20 10:17",
      "serviceId": "2_36",
      "tripId": "2_15148",
      "routeId": "2_0001",
      "headsign": "1 | Chantepie Rosa Parks"
    },
    {
      "arrival": "2015-03-20 10:27",
      "departure": "2015-03-20 10:27",
      "serviceId": "2_36",
      "tripId": "2_15143",
      "routeId": "2_0001",
      "headsign": "1 | Chantepie Rosa Parks"
    },
    {
      "arrival": "2015-03-20 10:37",
      "departure": "2015-03-20 10:37",
      "serviceId": "2_36",
      "tripId": "2_15158",
      "routeId": "2_0001",
      "headsign": "1 | Chantepie Rosa Parks"
    },
    {
      "arrival": "2015-03-20 10:47",
      "departure": "2015-03-20 10:47",
      "serviceId": "2_36",
      "tripId": "2_15153",
      "routeId": "2_0001",
      "headsign": "1 | Chantepie Rosa Parks"
    },
    {
      "arrival": "2015-03-20 10:57",
      "departure": "2015-03-20 10:57",
      "serviceId": "2_36",
      "tripId": "2_15168",
      "routeId": "2_0001",
      "headsign": "1 | Chantepie Rosa Parks"
    },
    {
      "arrival": "2015-03-20 11:07",
      "departure": "2015-03-20 11:07",
      "serviceId": "2_36",
      "tripId": "2_15163",
      "routeId": "2_0001",
      "headsign": "1 | Chantepie Rosa Parks"
    },
    {
      "arrival": "2015-03-20 11:17",
      "departure": "2015-03-20 11:17",
      "serviceId": "2_36",
      "tripId": "2_15178",
      "routeId": "2_0001",
      "headsign": "1 | Chantepie Rosa Parks"
    },
    {
      "arrival": "2015-03-20 11:27",
      "departure": "2015-03-20 11:27",
      "serviceId": "2_36",
      "tripId": "2_15173",
      "routeId": "2_0001",
      "headsign": "1 | Chantepie Rosa Parks"
    },
    {
      "arrival": "2015-03-20 11:37",
      "departure": "2015-03-20 11:37",
      "serviceId": "2_36",
      "tripId": "2_15188",
      "routeId": "2_0001",
      "headsign": "1 | Chantepie Rosa Parks"
    },
    {
      "arrival": "2015-03-20 11:47",
      "departure": "2015-03-20 11:47",
      "serviceId": "2_36",
      "tripId": "2_15183",
      "routeId": "2_0001",
      "headsign": "1 | Chantepie Rosa Parks"
    },
    {
      "arrival": "2015-03-20 11:56",
      "departure": "2015-03-20 11:56",
      "serviceId": "2_36",
      "tripId": "2_15193",
      "routeId": "2_0001",
      "headsign": "1 | Chantepie Rosa Parks"
    },
    {
      "arrival": "2015-03-20 12:05",
      "departure": "2015-03-20 12:05",
      "serviceId": "2_36",
      "tripId": "2_15483",
      "routeId": "2_0001",
      "headsign": "1 | Chantepie Rosa Parks"
    },
    {
      "arrival": "2015-03-20 12:14",
      "departure": "2015-03-20 12:14",
      "serviceId": "2_36",
      "tripId": "2_15478",
      "routeId": "2_0001",
      "headsign": "1 | Chantepie Rosa Parks"
    },
    {
      "arrival": "2015-03-20 12:23",
      "departure": "2015-03-20 12:23",
      "serviceId": "2_36",
      "tripId": "2_15248",
      "routeId": "2_0001",
      "headsign": "1 | Chantepie Rosa Parks"
    },
    {
      "arrival": "2015-03-20 12:33",
      "departure": "2015-03-20 12:33",
      "serviceId": "2_36",
      "tripId": "2_14958",
      "routeId": "2_0001",
      "headsign": "1 | Chantepie Rosa Parks"
    },
    {
      "arrival": "2015-03-20 12:42",
      "departure": "2015-03-20 12:42",
      "serviceId": "2_36",
      "tripId": "2_15488",
      "routeId": "2_0001",
      "headsign": "1 | Chantepie Rosa Parks"
    },
    {
      "arrival": "2015-03-20 12:52",
      "departure": "2015-03-20 12:52",
      "serviceId": "2_36",
      "tripId": "2_14953",
      "routeId": "2_0001",
      "headsign": "1 | Chantepie Rosa Parks"
    },
    {
      "arrival": "2015-03-20 13:01",
      "departure": "2015-03-20 13:01",
      "serviceId": "2_36",
      "tripId": "2_15503",
      "routeId": "2_0001",
      "headsign": "1 | Chantepie Rosa Parks"
    },
    {
      "arrival": "2015-03-20 13:11",
      "departure": "2015-03-20 13:11",
      "serviceId": "2_36",
      "tripId": "2_14998",
      "routeId": "2_0001",
      "headsign": "1 | Chantepie Rosa Parks"
    },
    {
      "arrival": "2015-03-20 13:21",
      "departure": "2015-03-20 13:21",
      "serviceId": "2_36",
      "tripId": "2_14973",
      "routeId": "2_0001",
      "headsign": "1 | Chantepie Rosa Parks"
    },
    {
      "arrival": "2015-03-20 13:30",
      "departure": "2015-03-20 13:30",
      "serviceId": "2_36",
      "tripId": "2_15723",
      "routeId": "2_0001",
      "headsign": "1 | Chantepie Rosa Parks"
    },
    {
      "arrival": "2015-03-20 13:39",
      "departure": "2015-03-20 13:39",
      "serviceId": "2_36",
      "tripId": "2_15498",
      "routeId": "2_0001",
      "headsign": "1 | Chantepie Rosa Parks"
    },
    {
      "arrival": "2015-03-20 13:48",
      "departure": "2015-03-20 13:48",
      "serviceId": "2_36",
      "tripId": "2_14983",
      "routeId": "2_0001",
      "headsign": "1 | Chantepie Rosa Parks"
    },
    {
      "arrival": "2015-03-20 13:58",
      "departure": "2015-03-20 13:58",
      "serviceId": "2_36",
      "tripId": "2_15708",
      "routeId": "2_0001",
      "headsign": "1 | Chantepie Rosa Parks"
    },
    {
      "arrival": "2015-03-20 14:07",
      "departure": "2015-03-20 14:07",
      "serviceId": "2_36",
      "tripId": "2_15733",
      "routeId": "2_0001",
      "headsign": "1 | Chantepie Rosa Parks"
    },
    {
      "arrival": "2015-03-20 14:15",
      "departure": "2015-03-20 14:15",
      "serviceId": "2_36",
      "tripId": "2_15928",
      "routeId": "2_0001",
      "headsign": "1 | Chantepie Rosa Parks"
    },
    {
      "arrival": "2015-03-20 14:24",
      "departure": "2015-03-20 14:24",
      "serviceId": "2_36",
      "tripId": "2_14963",
      "routeId": "2_0001",
      "headsign": "1 | Chantepie Rosa Parks"
    },
    {
      "arrival": "2015-03-20 14:33",
      "departure": "2015-03-20 14:33",
      "serviceId": "2_36",
      "tripId": "2_15543",
      "routeId": "2_0001",
      "headsign": "1 | Chantepie Rosa Parks"
    },
    {
      "arrival": "2015-03-20 14:42",
      "departure": "2015-03-20 14:42",
      "serviceId": "2_36",
      "tripId": "2_15643",
      "routeId": "2_0001",
      "headsign": "1 | Chantepie Rosa Parks"
    },
    {
      "arrival": "2015-03-20 14:51",
      "departure": "2015-03-20 14:51",
      "serviceId": "2_36",
      "tripId": "2_15568",
      "routeId": "2_0001",
      "headsign": "1 | Chantepie Rosa Parks"
    },
    {
      "arrival": "2015-03-20 15:00",
      "departure": "2015-03-20 15:00",
      "serviceId": "2_36",
      "tripId": "2_15013",
      "routeId": "2_0001",
      "headsign": "1 | Chantepie Rosa Parks"
    },
    {
      "arrival": "2015-03-20 15:09",
      "departure": "2015-03-20 15:09",
      "serviceId": "2_36",
      "tripId": "2_15933",
      "routeId": "2_0001",
      "headsign": "1 | Chantepie Rosa Parks"
    },
    {
      "arrival": "2015-03-20 15:19",
      "departure": "2015-03-20 15:19",
      "serviceId": "2_36",
      "tripId": "2_15713",
      "routeId": "2_0001",
      "headsign": "1 | Chantepie Rosa Parks"
    },
    {
      "arrival": "2015-03-20 15:28",
      "departure": "2015-03-20 15:28",
      "serviceId": "2_36",
      "tripId": "2_15043",
      "routeId": "2_0001",
      "headsign": "1 | Chantepie Rosa Parks"
    },
    {
      "arrival": "2015-03-20 15:37",
      "departure": "2015-03-20 15:37",
      "serviceId": "2_36",
      "tripId": "2_15058",
      "routeId": "2_0001",
      "headsign": "1 | Chantepie Rosa Parks"
    },
    {
      "arrival": "2015-03-20 15:45",
      "departure": "2015-03-20 15:45",
      "serviceId": "2_36",
      "tripId": "2_15673",
      "routeId": "2_0001",
      "headsign": "1 | Chantepie Rosa Parks"
    },
    {
      "arrival": "2015-03-20 15:52",
      "departure": "2015-03-20 15:52",
      "serviceId": "2_36",
      "tripId": "2_15518",
      "routeId": "2_0001",
      "headsign": "1 | Chantepie Rosa Parks"
    },
    {
      "arrival": "2015-03-20 16:00",
      "departure": "2015-03-20 16:00",
      "serviceId": "2_36",
      "tripId": "2_15913",
      "routeId": "2_0001",
      "headsign": "1 | Chantepie Rosa Parks"
    },
    {
      "arrival": "2015-03-20 16:08",
      "departure": "2015-03-20 16:08",
      "serviceId": "2_36",
      "tripId": "2_14993",
      "routeId": "2_0001",
      "headsign": "1 | Chantepie Rosa Parks"
    },
    {
      "arrival": "2015-03-20 16:16",
      "departure": "2015-03-20 16:16",
      "serviceId": "2_36",
      "tripId": "2_15053",
      "routeId": "2_0001",
      "headsign": "1 | Chantepie Rosa Parks"
    },
    {
      "arrival": "2015-03-20 16:23",
      "departure": "2015-03-20 16:23",
      "serviceId": "2_36",
      "tripId": "2_15303",
      "routeId": "2_0001",
      "headsign": "1 | Chantepie Rosa Parks"
    },
    {
      "arrival": "2015-03-20 16:30",
      "departure": "2015-03-20 16:30",
      "serviceId": "2_36",
      "tripId": "2_15603",
      "routeId": "2_0001",
      "headsign": "1 | Chantepie Rosa Parks"
    },
    {
      "arrival": "2015-03-20 16:39",
      "departure": "2015-03-20 16:39",
      "serviceId": "2_36",
      "tripId": "2_15598",
      "routeId": "2_0001",
      "headsign": "1 | Chantepie Rosa Parks"
    },
    {
      "arrival": "2015-03-20 16:47",
      "departure": "2015-03-20 16:47",
      "serviceId": "2_36",
      "tripId": "2_15593",
      "routeId": "2_0001",
      "headsign": "1 | Chantepie Rosa Parks"
    },
    {
      "arrival": "2015-03-20 16:55",
      "departure": "2015-03-20 16:55",
      "serviceId": "2_36",
      "tripId": "2_15583",
      "routeId": "2_0001",
      "headsign": "1 | Chantepie Rosa Parks"
    },
    {
      "arrival": "2015-03-20 17:03",
      "departure": "2015-03-20 17:03",
      "serviceId": "2_36",
      "tripId": "2_15238",
      "routeId": "2_0001",
      "headsign": "1 | Chantepie Rosa Parks"
    },
    {
      "arrival": "2015-03-20 17:12",
      "departure": "2015-03-20 17:12",
      "serviceId": "2_36",
      "tripId": "2_15793",
      "routeId": "2_0001",
      "headsign": "1 | Chantepie Rosa Parks"
    },
    {
      "arrival": "2015-03-20 17:20",
      "departure": "2015-03-20 17:20",
      "serviceId": "2_36",
      "tripId": "2_15798",
      "routeId": "2_0001",
      "headsign": "1 | Chantepie Rosa Parks"
    },
    {
      "arrival": "2015-03-20 17:28",
      "departure": "2015-03-20 17:28",
      "serviceId": "2_36",
      "tripId": "2_15283",
      "routeId": "2_0001",
      "headsign": "1 | Chantepie Rosa Parks"
    },
    {
      "arrival": "2015-03-20 17:36",
      "departure": "2015-03-20 17:36",
      "serviceId": "2_36",
      "tripId": "2_15288",
      "routeId": "2_0001",
      "headsign": "1 | Chantepie Rosa Parks"
    },
    {
      "arrival": "2015-03-20 17:44",
      "departure": "2015-03-20 17:44",
      "serviceId": "2_36",
      "tripId": "2_15293",
      "routeId": "2_0001",
      "headsign": "1 | Chantepie Rosa Parks"
    },
    {
      "arrival": "2015-03-20 17:53",
      "departure": "2015-03-20 17:53",
      "serviceId": "2_36",
      "tripId": "2_15298",
      "routeId": "2_0001",
      "headsign": "1 | Chantepie Rosa Parks"
    },
    {
      "arrival": "2015-03-20 18:02",
      "departure": "2015-03-20 18:02",
      "serviceId": "2_36",
      "tripId": "2_15748",
      "routeId": "2_0001",
      "headsign": "1 | Chantepie Rosa Parks"
    },
    {
      "arrival": "2015-03-20 18:11",
      "departure": "2015-03-20 18:11",
      "serviceId": "2_36",
      "tripId": "2_15753",
      "routeId": "2_0001",
      "headsign": "1 | Chantepie Rosa Parks"
    },
    {
      "arrival": "2015-03-20 18:20",
      "departure": "2015-03-20 18:20",
      "serviceId": "2_36",
      "tripId": "2_15758",
      "routeId": "2_0001",
      "headsign": "1 | Chantepie Rosa Parks"
    },
    {
      "arrival": "2015-03-20 18:28",
      "departure": "2015-03-20 18:28",
      "serviceId": "2_36",
      "tripId": "2_15763",
      "routeId": "2_0001",
      "headsign": "1 | Chantepie Rosa Parks"
    },
    {
      "arrival": "2015-03-20 18:37",
      "departure": "2015-03-20 18:37",
      "serviceId": "2_36",
      "tripId": "2_15768",
      "routeId": "2_0001",
      "headsign": "1 | Chantepie Rosa Parks"
    },
    {
      "arrival": "2015-03-20 18:45",
      "departure": "2015-03-20 18:45",
      "serviceId": "2_36",
      "tripId": "2_15893",
      "routeId": "2_0001",
      "headsign": "1 | Chantepie Rosa Parks"
    },
    {
      "arrival": "2015-03-20 18:55",
      "departure": "2015-03-20 18:55",
      "serviceId": "2_36",
      "tripId": "2_15773",
      "routeId": "2_0001",
      "headsign": "1 | Chantepie Rosa Parks"
    },
    {
      "arrival": "2015-03-20 19:05",
      "departure": "2015-03-20 19:05",
      "serviceId": "2_36",
      "tripId": "2_15308",
      "routeId": "2_0001",
      "headsign": "1 | Chantepie Rosa Parks"
    },
    {
      "arrival": "2015-03-20 19:17",
      "departure": "2015-03-20 19:17",
      "serviceId": "2_36",
      "tripId": "2_15313",
      "routeId": "2_0001",
      "headsign": "1 | Chantepie Rosa Parks"
    },
    {
      "arrival": "2015-03-20 19:29",
      "departure": "2015-03-20 19:29",
      "serviceId": "2_36",
      "tripId": "2_15318",
      "routeId": "2_0001",
      "headsign": "1 | Chantepie Rosa Parks"
    },
    {
      "arrival": "2015-03-20 19:41",
      "departure": "2015-03-20 19:41",
      "serviceId": "2_36",
      "tripId": "2_15323",
      "routeId": "2_0001",
      "headsign": "1 | Chantepie Rosa Parks"
    },
    {
      "arrival": "2015-03-20 19:54",
      "departure": "2015-03-20 19:54",
      "serviceId": "2_36",
      "tripId": "2_15328",
      "routeId": "2_0001",
      "headsign": "1 | Chantepie Rosa Parks"
    },
    {
      "arrival": "2015-03-20 20:06",
      "departure": "2015-03-20 20:06",
      "serviceId": "2_36",
      "tripId": "2_15333",
      "routeId": "2_0001",
      "headsign": "1 | Chantepie Rosa Parks"
    },
    {
      "arrival": "2015-03-20 20:21",
      "departure": "2015-03-20 20:21",
      "serviceId": "2_36",
      "tripId": "2_15838",
      "routeId": "2_0001",
      "headsign": "1 | Chantepie Rosa Parks"
    },
    {
      "arrival": "2015-03-20 20:46",
      "departure": "2015-03-20 20:46",
      "serviceId": "2_36",
      "tripId": "2_15873",
      "routeId": "2_0001",
      "headsign": "1 | Chantepie Rosa Parks"
    },
    {
      "arrival": "2015-03-20 21:23",
      "departure": "2015-03-20 21:23",
      "serviceId": "2_36",
      "tripId": "2_15843",
      "routeId": "2_0001",
      "headsign": "1 | Chantepie Rosa Parks"
    },
    {
      "arrival": "2015-03-20 21:58",
      "departure": "2015-03-20 21:58",
      "serviceId": "2_36",
      "tripId": "2_15888",
      "routeId": "2_0001",
      "headsign": "1 | Chantepie Rosa Parks"
    },
    {
      "arrival": "2015-03-20 22:33",
      "departure": "2015-03-20 22:33",
      "serviceId": "2_36",
      "tripId": "2_15818",
      "routeId": "2_0001",
      "headsign": "1 | Chantepie Rosa Parks"
    },
    {
      "arrival": "2015-03-20 23:13",
      "departure": "2015-03-20 23:13",
      "serviceId": "2_36",
      "tripId": "2_15833",
      "routeId": "2_0001",
      "headsign": "1 | Chantepie Rosa Parks"
    },
    {
      "arrival": "2015-03-20 23:48",
      "departure": "2015-03-20 23:48",
      "serviceId": "2_36",
      "tripId": "2_15853",
      "routeId": "2_0001",
      "headsign": "1 | Rennes République"
    },
    {
      "arrival": "2015-03-21 00:17",
      "departure": "2015-03-21 00:17",
      "serviceId": "2_36",
      "tripId": "2_15808",
      "routeId": "2_0001",
      "headsign": "1 | Chantepie Rosa Parks"
    },
    {
      "arrival": "2015-03-21 01:02",
      "departure": "2015-03-21 01:02",
      "serviceId": "2_37",
      "tripId": "2_28464",
      "routeId": "2_0001",
      "headsign": "1 | Chantepie Rosa Parks"
    }
  ]
}