{
  "date": "2014-05-03 00:00",
  "stop": {
    "id": "2_3010",
    "lat": 48.08815767,
    "lon": -1.61691516,
    "name": "Chantepie Eglise",
    "code": 3010
  },
  "routes": [
    {
      "id": "2_0001",
      "textColor": "FFFFFF",
      "color": "90C01B",
      "description": "Majeure",
      "longName": "Cesson-Sévigné (Champs Blancs) \u003c\u003e Chantepie (Rosa Parks)",
      "shortName": "1",
      "type": 3,
      "agencyId": "2"
    },
    {
      "id": "2_0033",
      "textColor": "DF171C",
      "color": "FEF466",
      "description": "Inter-quartiers",
      "longName": "Saint-Jacques-de-la-Lande / Bréquigny \u003c\u003e La Poterie / Chantepie (Cucé)",
      "shortName": "33",
      "type": 3,
      "agencyId": "2"
    }
  ],
  "stopTimes": [
    {
      "arrival": "2014-05-03 06:42",
      "departure": "2014-05-03 06:42",
      "serviceId": "2_6",
      "tripId": "2_7105",
      "routeId": "2_0001",
      "headsign": "1 | Chantepie Rosa Parks"
    },
    {
      "arrival": "2014-05-03 07:25",
      "departure": "2014-05-03 07:25",
      "serviceId": "2_6",
      "tripId": "2_7107",
      "routeId": "2_0001",
      "headsign": "1 | Chantepie Rosa Parks"
    },
    {
      "arrival": "2014-05-03 07:42",
      "departure": "2014-05-03 07:42",
      "serviceId": "2_6",
      "tripId": "2_7109",
      "routeId": "2_0001",
      "headsign": "1 | Chantepie Rosa Parks"
    },
    {
      "arrival": "2014-05-03 07:54",
      "departure": "2014-05-03 07:54",
      "serviceId": "2_6",
      "tripId": "2_22474",
      "routeId": "2_0033",
      "headsign": "33 | Chantepie Cucé"
    },
    {
      "arrival": "2014-05-03 08:03",
      "departure": "2014-05-03 08:03",
      "serviceId": "2_6",
      "tripId": "2_7111",
      "routeId": "2_0001",
      "headsign": "1 | Chantepie Rosa Parks"
    },
    {
      "arrival": "2014-05-03 08:24",
      "departure": "2014-05-03 08:24",
      "serviceId": "2_6",
      "tripId": "2_7113",
      "routeId": "2_0001",
      "headsign": "1 | Chantepie Rosa Parks"
    },
    {
      "arrival": "2014-05-03 08:29",
      "departure": "2014-05-03 08:29",
      "serviceId": "2_6",
      "tripId": "2_22476",
      "routeId": "2_0033",
      "headsign": "33 | Chantepie Cucé"
    },
    {
      "arrival": "2014-05-03 08:44",
      "departure": "2014-05-03 08:44",
      "serviceId": "2_6",
      "tripId": "2_7115",
      "routeId": "2_0001",
      "headsign": "1 | Chantepie Rosa Parks"
    },
    {
      "arrival": "2014-05-03 09:00",
      "departure": "2014-05-03 09:00",
      "serviceId": "2_6",
      "tripId": "2_7117",
      "routeId": "2_0001",
      "headsign": "1 | Chantepie Rosa Parks"
    },
    {
      "arrival": "2014-05-03 09:05",
      "departure": "2014-05-03 09:05",
      "serviceId": "2_6",
      "tripId": "2_22478",
      "routeId": "2_0033",
      "headsign": "33 | Chantepie Cucé"
    },
    {
      "arrival": "2014-05-03 09:15",
      "departure": "2014-05-03 09:15",
      "serviceId": "2_6",
      "tripId": "2_7303",
      "routeId": "2_0001",
      "headsign": "1 | Chantepie Rosa Parks"
    },
    {
      "arrival": "2014-05-03 09:30",
      "departure": "2014-05-03 09:30",
      "serviceId": "2_6",
      "tripId": "2_7119",
      "routeId": "2_0001",
      "headsign": "1 | Chantepie Rosa Parks"
    },
    {
      "arrival": "2014-05-03 09:35",
      "departure": "2014-05-03 09:35",
      "serviceId": "2_6",
      "tripId": "2_22480",
      "routeId": "2_0033",
      "headsign": "33 | Chantepie Cucé"
    },
    {
      "arrival": "2014-05-03 09:47",
      "departure": "2014-05-03 09:47",
      "serviceId": "2_6",
      "tripId": "2_7121",
      "routeId": "2_0001",
      "headsign": "1 | Chantepie Rosa Parks"
    },
    {
      "arrival": "2014-05-03 10:01",
      "departure": "2014-05-03 10:01",
      "serviceId": "2_6",
      "tripId": "2_7123",
      "routeId": "2_0001",
      "headsign": "1 | Chantepie Rosa Parks"
    },
    {
      "arrival": "2014-05-03 10:06",
      "departure": "2014-05-03 10:06",
      "serviceId": "2_6",
      "tripId": "2_22482",
      "routeId": "2_0033",
      "headsign": "33 | Chantepie Cucé"
    },
    {
      "arrival": "2014-05-03 10:16",
      "departure": "2014-05-03 10:16",
      "serviceId": "2_6",
      "tripId": "2_7125",
      "routeId": "2_0001",
      "headsign": "1 | Chantepie Rosa Parks"
    },
    {
      "arrival": "2014-05-03 10:28",
      "departure": "2014-05-03 10:28",
      "serviceId": "2_6",
      "tripId": "2_7127",
      "routeId": "2_0001",
      "headsign": "1 | Chantepie Rosa Parks"
    },
    {
      "arrival": "2014-05-03 10:33",
      "departure": "2014-05-03 10:33",
      "serviceId": "2_6",
      "tripId": "2_22484",
      "routeId": "2_0033",
      "headsign": "33 | Chantepie Cucé"
    },
    {
      "arrival": "2014-05-03 10:45",
      "departure": "2014-05-03 10:45",
      "serviceId": "2_6",
      "tripId": "2_7129",
      "routeId": "2_0001",
      "headsign": "1 | Chantepie Rosa Parks"
    },
    {
      "arrival": "2014-05-03 10:54",
      "departure": "2014-05-03 10:54",
      "serviceId": "2_6",
      "tripId": "2_22486",
      "routeId": "2_0033",
      "headsign": "33 | Chantepie Cucé"
    },
    {
      "arrival": "2014-05-03 11:01",
      "departure": "2014-05-03 11:01",
      "serviceId": "2_6",
      "tripId": "2_7131",
      "routeId": "2_0001",
      "headsign": "1 | Chantepie Rosa Parks"
    },
    {
      "arrival": "2014-05-03 11:14",
      "departure": "2014-05-03 11:14",
      "serviceId": "2_6",
      "tripId": "2_22488",
      "routeId": "2_0033",
      "headsign": "33 | Chantepie Cucé"
    },
    {
      "arrival": "2014-05-03 11:16",
      "departure": "2014-05-03 11:16",
      "serviceId": "2_6",
      "tripId": "2_7133",
      "routeId": "2_0001",
      "headsign": "1 | Chantepie Rosa Parks"
    },
    {
      "arrival": "2014-05-03 11:32",
      "departure": "2014-05-03 11:32",
      "serviceId": "2_6",
      "tripId": "2_7135",
      "routeId": "2_0001",
      "headsign": "1 | Chantepie Rosa Parks"
    },
    {
      "arrival": "2014-05-03 11:34",
      "departure": "2014-05-03 11:34",
      "serviceId": "2_6",
      "tripId": "2_22490",
      "routeId": "2_0033",
      "headsign": "33 | Chantepie Cucé"
    },
    {
      "arrival": "2014-05-03 11:48",
      "departure": "2014-05-03 11:48",
      "serviceId": "2_6",
      "tripId": "2_7137",
      "routeId": "2_0001",
      "headsign": "1 | Chantepie Rosa Parks"
    },
    {
      "arrival": "2014-05-03 11:58",
      "departure": "2014-05-03 11:58",
      "serviceId": "2_6",
      "tripId": "2_22492",
      "routeId": "2_0033",
      "headsign": "33 | Chantepie Cucé"
    },
    {
      "arrival": "2014-05-03 12:03",
      "departure": "2014-05-03 12:03",
      "serviceId": "2_6",
      "tripId": "2_7139",
      "routeId": "2_0001",
      "headsign": "1 | Chantepie Rosa Parks"
    },
    {
      "arrival": "2014-05-03 12:18",
      "departure": "2014-05-03 12:18",
      "serviceId": "2_6",
      "tripId": "2_7141",
      "routeId": "2_0001",
      "headsign": "1 | Chantepie Rosa Parks"
    },
    {
      "arrival": "2014-05-03 12:19",
      "departure": "2014-05-03 12:19",
      "serviceId": "2_6",
      "tripId": "2_22494",
      "routeId": "2_0033",
      "headsign": "33 | Chantepie Cucé"
    },
    {
      "arrival": "2014-05-03 12:33",
      "departure": "2014-05-03 12:33",
      "serviceId": "2_6",
      "tripId": "2_7143",
      "routeId": "2_0001",
      "headsign": "1 | Chantepie Rosa Parks"
    },
    {
      "arrival": "2014-05-03 12:38",
      "departure": "2014-05-03 12:38",
      "serviceId": "2_6",
      "tripId": "2_22496",
      "routeId": "2_0033",
      "headsign": "33 | Chantepie Cucé"
    },
    {
      "arrival": "2014-05-03 12:48",
      "departure": "2014-05-03 12:48",
      "serviceId": "2_6",
      "tripId": "2_7145",
      "routeId": "2_0001",
      "headsign": "1 | Chantepie Rosa Parks"
    },
    {
      "arrival": "2014-05-03 12:58",
      "departure": "2014-05-03 12:58",
      "serviceId": "2_6",
      "tripId": "2_22470",
      "routeId": "2_0033",
      "headsign": "33 | Chantepie Cucé"
    },
    {
      "arrival": "2014-05-03 13:03",
      "departure": "2014-05-03 13:03",
      "serviceId": "2_6",
      "tripId": "2_7147",
      "routeId": "2_0001",
      "headsign": "1 | Chantepie Rosa Parks"
    },
    {
      "arrival": "2014-05-03 13:17",
      "departure": "2014-05-03 13:17",
      "serviceId": "2_6",
      "tripId": "2_7149",
      "routeId": "2_0001",
      "headsign": "1 | Chantepie Rosa Parks"
    },
    {
      "arrival": "2014-05-03 13:18",
      "departure": "2014-05-03 13:18",
      "serviceId": "2_6",
      "tripId": "2_22498",
      "routeId": "2_0033",
      "headsign": "33 | Chantepie Cucé"
    },
    {
      "arrival": "2014-05-03 13:32",
      "departure": "2014-05-03 13:32",
      "serviceId": "2_6",
      "tripId": "2_7151",
      "routeId": "2_0001",
      "headsign": "1 | Chantepie Rosa Parks"
    },
    {
      "arrival": "2014-05-03 13:44",
      "departure": "2014-05-03 13:44",
      "serviceId": "2_6",
      "tripId": "2_22500",
      "routeId": "2_0033",
      "headsign": "33 | Chantepie Cucé"
    },
    {
      "arrival": "2014-05-03 13:47",
      "departure": "2014-05-03 13:47",
      "serviceId": "2_6",
      "tripId": "2_7153",
      "routeId": "2_0001",
      "headsign": "1 | Chantepie Rosa Parks"
    },
    {
      "arrival": "2014-05-03 14:02",
      "departure": "2014-05-03 14:02",
      "serviceId": "2_6",
      "tripId": "2_7155",
      "routeId": "2_0001",
      "headsign": "1 | Chantepie Rosa Parks"
    },
    {
      "arrival": "2014-05-03 14:05",
      "departure": "2014-05-03 14:05",
      "serviceId": "2_6",
      "tripId": "2_22502",
      "routeId": "2_0033",
      "headsign": "33 | Chantepie Cucé"
    },
    {
      "arrival": "2014-05-03 14:17",
      "departure": "2014-05-03 14:17",
      "serviceId": "2_6",
      "tripId": "2_7205",
      "routeId": "2_0001",
      "headsign": "1 | Chantepie Rosa Parks"
    },
    {
      "arrival": "2014-05-03 14:24",
      "departure": "2014-05-03 14:24",
      "serviceId": "2_6",
      "tripId": "2_22504",
      "routeId": "2_0033",
      "headsign": "33 | Chantepie Cucé"
    },
    {
      "arrival": "2014-05-03 14:30",
      "departure": "2014-05-03 14:30",
      "serviceId": "2_6",
      "tripId": "2_7207",
      "routeId": "2_0001",
      "headsign": "1 | Chantepie Rosa Parks"
    },
    {
      "arrival": "2014-05-03 14:42",
      "departure": "2014-05-03 14:42",
      "serviceId": "2_6",
      "tripId": "2_7209",
      "routeId": "2_0001",
      "headsign": "1 | Chantepie Rosa Parks"
    },
    {
      "arrival": "2014-05-03 14:47",
      "departure": "2014-05-03 14:47",
      "serviceId": "2_6",
      "tripId": "2_22506",
      "routeId": "2_0033",
      "headsign": "33 | Chantepie Cucé"
    },
    {
      "arrival": "2014-05-03 14:54",
      "departure": "2014-05-03 14:54",
      "serviceId": "2_6",
      "tripId": "2_7211",
      "routeId": "2_0001",
      "headsign": "1 | Chantepie Rosa Parks"
    },
    {
      "arrival": "2014-05-03 15:06",
      "departure": "2014-05-03 15:06",
      "serviceId": "2_6",
      "tripId": "2_7213",
      "routeId": "2_0001",
      "headsign": "1 | Chantepie Rosa Parks"
    },
    {
      "arrival": "2014-05-03 15:07",
      "departure": "2014-05-03 15:07",
      "serviceId": "2_6",
      "tripId": "2_22508",
      "routeId": "2_0033",
      "headsign": "33 | Chantepie Cucé"
    },
    {
      "arrival": "2014-05-03 15:18",
      "departure": "2014-05-03 15:18",
      "serviceId": "2_6",
      "tripId": "2_7215",
      "routeId": "2_0001",
      "headsign": "1 | Chantepie Rosa Parks"
    },
    {
      "arrival": "2014-05-03 15:27",
      "departure": "2014-05-03 15:27",
      "serviceId": "2_6",
      "tripId": "2_22510",
      "routeId": "2_0033",
      "headsign": "33 | Chantepie Cucé"
    },
    {
      "arrival": "2014-05-03 15:31",
      "departure": "2014-05-03 15:31",
      "serviceId": "2_6",
      "tripId": "2_7217",
      "routeId": "2_0001",
      "headsign": "1 | Chantepie Rosa Parks"
    },
    {
      "arrival": "2014-05-03 15:43",
      "departure": "2014-05-03 15:43",
      "serviceId": "2_6",
      "tripId": "2_7219",
      "routeId": "2_0001",
      "headsign": "1 | Chantepie Rosa Parks"
    },
    {
      "arrival": "2014-05-03 15:47",
      "departure": "2014-05-03 15:47",
      "serviceId": "2_6",
      "tripId": "2_22512",
      "routeId": "2_0033",
      "headsign": "33 | Chantepie Cucé"
    },
    {
      "arrival": "2014-05-03 15:55",
      "departure": "2014-05-03 15:55",
      "serviceId": "2_6",
      "tripId": "2_7221",
      "routeId": "2_0001",
      "headsign": "1 | Chantepie Rosa Parks"
    },
    {
      "arrival": "2014-05-03 16:07",
      "departure": "2014-05-03 16:07",
      "serviceId": "2_6",
      "tripId": "2_22514",
      "routeId": "2_0033",
      "headsign": "33 | Chantepie Cucé"
    },
    {
      "arrival": "2014-05-03 16:08",
      "departure": "2014-05-03 16:08",
      "serviceId": "2_6",
      "tripId": "2_7223",
      "routeId": "2_0001",
      "headsign": "1 | Chantepie Rosa Parks"
    },
    {
      "arrival": "2014-05-03 16:20",
      "departure": "2014-05-03 16:20",
      "serviceId": "2_6",
      "tripId": "2_7225",
      "routeId": "2_0001",
      "headsign": "1 | Chantepie Rosa Parks"
    },
    {
      "arrival": "2014-05-03 16:29",
      "departure": "2014-05-03 16:29",
      "serviceId": "2_6",
      "tripId": "2_22516",
      "routeId": "2_0033",
      "headsign": "33 | Chantepie Cucé"
    },
    {
      "arrival": "2014-05-03 16:32",
      "departure": "2014-05-03 16:32",
      "serviceId": "2_6",
      "tripId": "2_7227",
      "routeId": "2_0001",
      "headsign": "1 | Chantepie Rosa Parks"
    },
    {
      "arrival": "2014-05-03 16:44",
      "departure": "2014-05-03 16:44",
      "serviceId": "2_6",
      "tripId": "2_7229",
      "routeId": "2_0001",
      "headsign": "1 | Chantepie Rosa Parks"
    },
    {
      "arrival": "2014-05-03 16:49",
      "departure": "2014-05-03 16:49",
      "serviceId": "2_6",
      "tripId": "2_22518",
      "routeId": "2_0033",
      "headsign": "33 | Chantepie Cucé"
    },
    {
      "arrival": "2014-05-03 16:57",
      "departure": "2014-05-03 16:57",
      "serviceId": "2_6",
      "tripId": "2_7231",
      "routeId": "2_0001",
      "headsign": "1 | Chantepie Rosa Parks"
    },
    {
      "arrival": "2014-05-03 17:10",
      "departure": "2014-05-03 17:10",
      "serviceId": "2_6",
      "tripId": "2_7233",
      "routeId": "2_0001",
      "headsign": "1 | Chantepie Rosa Parks"
    },
    {
      "arrival": "2014-05-03 17:11",
      "departure": "2014-05-03 17:11",
      "serviceId": "2_6",
      "tripId": "2_22520",
      "routeId": "2_0033",
      "headsign": "33 | Chantepie Cucé"
    },
    {
      "arrival": "2014-05-03 17:23",
      "departure": "2014-05-03 17:23",
      "serviceId": "2_6",
      "tripId": "2_7235",
      "routeId": "2_0001",
      "headsign": "1 | Chantepie Rosa Parks"
    },
    {
      "arrival": "2014-05-03 17:32",
      "departure": "2014-05-03 17:32",
      "serviceId": "2_6",
      "tripId": "2_22522",
      "routeId": "2_0033",
      "headsign": "33 | Chantepie Cucé"
    },
    {
      "arrival": "2014-05-03 17:36",
      "departure": "2014-05-03 17:36",
      "serviceId": "2_6",
      "tripId": "2_7237",
      "routeId": "2_0001",
      "headsign": "1 | Chantepie Rosa Parks"
    },
    {
      "arrival": "2014-05-03 17:48",
      "departure": "2014-05-03 17:48",
      "serviceId": "2_6",
      "tripId": "2_7239",
      "routeId": "2_0001",
      "headsign": "1 | Chantepie Rosa Parks"
    },
    {
      "arrival": "2014-05-03 17:52",
      "departure": "2014-05-03 17:52",
      "serviceId": "2_6",
      "tripId": "2_22524",
      "routeId": "2_0033",
      "headsign": "33 | Chantepie Cucé"
    },
    {
      "arrival": "2014-05-03 18:00",
      "departure": "2014-05-03 18:00",
      "serviceId": "2_6",
      "tripId": "2_7241",
      "routeId": "2_0001",
      "headsign": "1 | Chantepie Rosa Parks"
    },
    {
      "arrival": "2014-05-03 18:12",
      "departure": "2014-05-03 18:12",
      "serviceId": "2_6",
      "tripId": "2_22526",
      "routeId": "2_0033",
      "headsign": "33 | Chantepie Cucé"
    },
    {
      "arrival": "2014-05-03 18:13",
      "departure": "2014-05-03 18:13",
      "serviceId": "2_6",
      "tripId": "2_7243",
      "routeId": "2_0001",
      "headsign": "1 | Chantepie Rosa Parks"
    },
    {
      "arrival": "2014-05-03 18:25",
      "departure": "2014-05-03 18:25",
      "serviceId": "2_6",
      "tripId": "2_7245",
      "routeId": "2_0001",
      "headsign": "1 | Chantepie Rosa Parks"
    },
    {
      "arrival": "2014-05-03 18:31",
      "departure": "2014-05-03 18:31",
      "serviceId": "2_6",
      "tripId": "2_22528",
      "routeId": "2_0033",
      "headsign": "33 | Chantepie Cucé"
    },
    {
      "arrival": "2014-05-03 18:38",
      "departure": "2014-05-03 18:38",
      "serviceId": "2_6",
      "tripId": "2_7247",
      "routeId": "2_0001",
      "headsign": "1 | Chantepie Rosa Parks"
    },
    {
      "arrival": "2014-05-03 18:48",
      "departure": "2014-05-03 18:48",
      "serviceId": "2_6",
      "tripId": "2_22530",
      "routeId": "2_0033",
      "headsign": "33 | Chantepie Cucé"
    },
    {
      "arrival": "2014-05-03 18:49",
      "departure": "2014-05-03 18:49",
      "serviceId": "2_6",
      "tripId": "2_7249",
      "routeId": "2_0001",
      "headsign": "1 | Chantepie Rosa Parks"
    },
    {
      "arrival": "2014-05-03 19:02",
      "departure": "2014-05-03 19:02",
      "serviceId": "2_6",
      "tripId": "2_7251",
      "routeId": "2_0001",
      "headsign": "1 | Chantepie Rosa Parks"
    },
    {
      "arrival": "2014-05-03 19:05",
      "departure": "2014-05-03 19:05",
      "serviceId": "2_6",
      "tripId": "2_22532",
      "routeId": "2_0033",
      "headsign": "33 | Chantepie Cucé"
    },
    {
      "arrival": "2014-05-03 19:17",
      "departure": "2014-05-03 19:17",
      "serviceId": "2_6",
      "tripId": "2_7253",
      "routeId": "2_0001",
      "headsign": "1 | Chantepie Rosa Parks"
    },
    {
      "arrival": "2014-05-03 19:24",
      "departure": "2014-05-03 19:24",
      "serviceId": "2_6",
      "tripId": "2_22534",
      "routeId": "2_0033",
      "headsign": "33 | Chantepie Cucé"
    },
    {
      "arrival": "2014-05-03 19:32",
      "departure": "2014-05-03 19:32",
      "serviceId": "2_6",
      "tripId": "2_7305",
      "routeId": "2_0001",
      "headsign": "1 | Chantepie Rosa Parks"
    },
    {
      "arrival": "2014-05-03 19:42",
      "departure": "2014-05-03 19:42",
      "serviceId": "2_6",
      "tripId": "2_22536",
      "routeId": "2_0033",
      "headsign": "33 | Chantepie Cucé"
    },
    {
      "arrival": "2014-05-03 19:47",
      "departure": "2014-05-03 19:47",
      "serviceId": "2_6",
      "tripId": "2_7255",
      "routeId": "2_0001",
      "headsign": "1 | Chantepie Rosa Parks"
    },
    {
      "arrival": "2014-05-03 20:01",
      "departure": "2014-05-03 20:01",
      "serviceId": "2_6",
      "tripId": "2_22538",
      "routeId": "2_0033",
      "headsign": "33 | Chantepie Cucé"
    },
    {
      "arrival": "2014-05-03 20:02",
      "departure": "2014-05-03 20:02",
      "serviceId": "2_6",
      "tripId": "2_7167",
      "routeId": "2_0001",
      "headsign": "1 | Chantepie Rosa Parks"
    },
    {
      "arrival": "2014-05-03 20:17",
      "departure": "2014-05-03 20:17",
      "serviceId": "2_6",
      "tripId": "2_7169",
      "routeId": "2_0001",
      "headsign": "1 | Chantepie Rosa Parks"
    },
    {
      "arrival": "2014-05-03 20:21",
      "departure": "2014-05-03 20:21",
      "serviceId": "2_6",
      "tripId": "2_22540",
      "routeId": "2_0033",
      "headsign": "33 | Chantepie Cucé"
    },
    {
      "arrival": "2014-05-03 20:31",
      "departure": "2014-05-03 20:31",
      "serviceId": "2_6",
      "tripId": "2_7171",
      "routeId": "2_0001",
      "headsign": "1 | Chantepie Rosa Parks"
    },
    {
      "arrival": "2014-05-03 20:44",
      "departure": "2014-05-03 20:44",
      "serviceId": "2_6",
      "tripId": "2_22542",
      "routeId": "2_0033",
      "headsign": "33 | Chantepie Cucé"
    },
    {
      "arrival": "2014-05-03 20:45",
      "departure": "2014-05-03 20:45",
      "serviceId": "2_6",
      "tripId": "2_7173",
      "routeId": "2_0001",
      "headsign": "1 | Chantepie Rosa Parks"
    },
    {
      "arrival": "2014-05-03 20:59",
      "departure": "2014-05-03 20:59",
      "serviceId": "2_6",
      "tripId": "2_7175",
      "routeId": "2_0001",
      "headsign": "1 | Chantepie Rosa Parks"
    },
    {
      "arrival": "2014-05-03 21:28",
      "departure": "2014-05-03 21:28",
      "serviceId": "2_6",
      "tripId": "2_7359",
      "routeId": "2_0001",
      "headsign": "1 | Chantepie Rosa Parks"
    },
    {
      "arrival": "2014-05-03 22:08",
      "departure": "2014-05-03 22:08",
      "serviceId": "2_6",
      "tripId": "2_7177",
      "routeId": "2_0001",
      "headsign": "1 | Chantepie Rosa Parks"
    },
    {
      "arrival": "2014-05-03 22:43",
      "departure": "2014-05-03 22:43",
      "serviceId": "2_6",
      "tripId": "2_7179",
      "routeId": "2_0001",
      "headsign": "1 | Chantepie Rosa Parks"
    },
    {
      "arrival": "2014-05-03 23:13",
      "departure": "2014-05-03 23:13",
      "serviceId": "2_6",
      "tripId": "2_7355",
      "routeId": "2_0001",
      "headsign": "1 | Chantepie Rosa Parks"
    },
    {
      "arrival": "2014-05-03 23:53",
      "departure": "2014-05-03 23:53",
      "serviceId": "2_6",
      "tripId": "2_7181",
      "routeId": "2_0001",
      "headsign": "1 | Chantepie Rosa Parks"
    },
    {
      "arrival": "2014-05-04 00:53",
      "departure": "2014-05-04 00:53",
      "serviceId": "2_6",
      "tripId": "2_7183",
      "routeId": "2_0001",
      "headsign": "1 | Chantepie Rosa Parks"
    },
    {
      "arrival": "2014-05-04 01:53",
      "departure": "2014-05-04 01:53",
      "serviceId": "2_6",
      "tripId": "2_7363",
      "routeId": "2_0001",
      "headsign": "1 | Chantepie Rosa Parks"
    }
  ]
}