{
  "date": "2014-06-08 00:00",
  "stop": {
    "id": "2_1096",
    "lat": 48.11820647,
    "lon": -1.68928315,
    "name": "Anatole France",
    "code": 1096
  },
  "routes": [
    {
      "id": "2_0002",
      "textColor": "FFFFFF",
      "color": "0083CD",
      "description": "Majeure",
      "longName": "Grand Quartier \u003c\u003e La Poterie / Haut Sancé",
      "shortName": "2",
      "type": 3,
      "agencyId": "2"
    }
  ],
  "stopTimes": [
    {
      "arrival": "2014-06-08 09:33",
      "departure": "2014-06-08 09:33",
      "serviceId": "2_5",
      "tripId": "2_27868",
      "routeId": "2_0002",
      "headsign": "2 | Grand Quartier"
    },
    {
      "arrival": "2014-06-08 10:38",
      "departure": "2014-06-08 10:38",
      "serviceId": "2_5",
      "tripId": "2_27869",
      "routeId": "2_0002",
      "headsign": "2 | Grand Quartier"
    },
    {
      "arrival": "2014-06-08 11:43",
      "departure": "2014-06-08 11:43",
      "serviceId": "2_5",
      "tripId": "2_27870",
      "routeId": "2_0002",
      "headsign": "2 | Grand Quartier"
    },
    {
      "arrival": "2014-06-08 12:49",
      "departure": "2014-06-08 12:49",
      "serviceId": "2_5",
      "tripId": "2_27871",
      "routeId": "2_0002",
      "headsign": "2 | Grand Quartier"
    },
    {
      "arrival": "2014-06-08 13:52",
      "departure": "2014-06-08 13:52",
      "serviceId": "2_5",
      "tripId": "2_27872",
      "routeId": "2_0002",
      "headsign": "2 | Grand Quartier"
    },
    {
      "arrival": "2014-06-08 14:37",
      "departure": "2014-06-08 14:37",
      "serviceId": "2_5",
      "tripId": "2_27873",
      "routeId": "2_0002",
      "headsign": "2 | Grand Quartier"
    },
    {
      "arrival": "2014-06-08 15:22",
      "departure": "2014-06-08 15:22",
      "serviceId": "2_5",
      "tripId": "2_27874",
      "routeId": "2_0002",
      "headsign": "2 | Grand Quartier"
    },
    {
      "arrival": "2014-06-08 16:07",
      "departure": "2014-06-08 16:07",
      "serviceId": "2_5",
      "tripId": "2_27875",
      "routeId": "2_0002",
      "headsign": "2 | Grand Quartier"
    },
    {
      "arrival": "2014-06-08 16:52",
      "departure": "2014-06-08 16:52",
      "serviceId": "2_5",
      "tripId": "2_27876",
      "routeId": "2_0002",
      "headsign": "2 | Grand Quartier"
    },
    {
      "arrival": "2014-06-08 17:37",
      "departure": "2014-06-08 17:37",
      "serviceId": "2_5",
      "tripId": "2_27877",
      "routeId": "2_0002",
      "headsign": "2 | Grand Quartier"
    },
    {
      "arrival": "2014-06-08 18:22",
      "departure": "2014-06-08 18:22",
      "serviceId": "2_5",
      "tripId": "2_27878",
      "routeId": "2_0002",
      "headsign": "2 | Grand Quartier"
    },
    {
      "arrival": "2014-06-08 19:07",
      "departure": "2014-06-08 19:07",
      "serviceId": "2_5",
      "tripId": "2_27879",
      "routeId": "2_0002",
      "headsign": "2 | Grand Quartier"
    },
    {
      "arrival": "2014-06-08 19:52",
      "departure": "2014-06-08 19:52",
      "serviceId": "2_5",
      "tripId": "2_27880",
      "routeId": "2_0002",
      "headsign": "2 | Grand Quartier"
    },
    {
      "arrival": "2014-06-08 20:32",
      "departure": "2014-06-08 20:32",
      "serviceId": "2_5",
      "tripId": "2_27881",
      "routeId": "2_0002",
      "headsign": "2 | Grand Quartier"
    },
    {
      "arrival": "2014-06-08 21:17",
      "departure": "2014-06-08 21:17",
      "serviceId": "2_5",
      "tripId": "2_27882",
      "routeId": "2_0002",
      "headsign": "2 | Grand Quartier"
    },
    {
      "arrival": "2014-06-08 22:17",
      "departure": "2014-06-08 22:17",
      "serviceId": "2_5",
      "tripId": "2_27883",
      "routeId": "2_0002",
      "headsign": "2 | Grand Quartier"
    },
    {
      "arrival": "2014-06-08 23:22",
      "departure": "2014-06-08 23:22",
      "serviceId": "2_5",
      "tripId": "2_27884",
      "routeId": "2_0002",
      "headsign": "2 | Grand Quartier"
    },
    {
      "arrival": "2014-06-09 00:42",
      "departure": "2014-06-09 00:42",
      "serviceId": "2_5",
      "tripId": "2_27885",
      "routeId": "2_0002",
      "headsign": "2 | Grand Quartier"
    }
  ]
}