{
  "date": "2014-05-09 00:00",
  "stop": {
    "id": "2_4163",
    "lat": 48.10829229,
    "lon": -1.50738732,
    "name": "Turbanière",
    "code": 4163
  },
  "routes": [
    {
      "id": "2_0011",
      "textColor": "FFFFFF",
      "color": "DC81AE",
      "description": "Urbaine",
      "longName": "ZI Ouest / Stade Rennais \u003c\u003e Saint-Saëns / ZI Sud-Est",
      "shortName": "11",
      "type": 3,
      "agencyId": "2"
    },
    {
      "id": "2_0067",
      "textColor": "FFFFFF",
      "color": "E0083B",
      "description": "Métropolitaine",
      "longName": "Rennes (République) \u003c\u003e Cesson-Sévigné / Brécé",
      "shortName": "67",
      "type": 3,
      "agencyId": "2"
    }
  ],
  "stopTimes": [
    {
      "arrival": "2014-05-09 07:09",
      "departure": "2014-05-09 07:09",
      "serviceId": "2_18",
      "tripId": "2_15041",
      "routeId": "2_0067",
      "headsign": "67 | Brécé"
    },
    {
      "arrival": "2014-05-09 07:48",
      "departure": "2014-05-09 07:48",
      "serviceId": "2_18",
      "tripId": "2_15046",
      "routeId": "2_0067",
      "headsign": "67 | Brécé"
    },
    {
      "arrival": "2014-05-09 08:11",
      "departure": "2014-05-09 08:11",
      "serviceId": "2_18",
      "tripId": "2_15051",
      "routeId": "2_0067",
      "headsign": "67 | Brécé"
    },
    {
      "arrival": "2014-05-09 08:32",
      "departure": "2014-05-09 08:32",
      "serviceId": "2_18",
      "tripId": "2_15006",
      "routeId": "2_0067",
      "headsign": "67 | Brécé"
    },
    {
      "arrival": "2014-05-09 08:52",
      "departure": "2014-05-09 08:52",
      "serviceId": "2_18",
      "tripId": "2_15001",
      "routeId": "2_0067",
      "headsign": "67 | Brécé"
    },
    {
      "arrival": "2014-05-09 09:12",
      "departure": "2014-05-09 09:12",
      "serviceId": "2_18",
      "tripId": "2_14986",
      "routeId": "2_0067",
      "headsign": "67 | Brécé"
    },
    {
      "arrival": "2014-05-09 09:47",
      "departure": "2014-05-09 09:47",
      "serviceId": "2_18",
      "tripId": "2_14996",
      "routeId": "2_0067",
      "headsign": "67 | Brécé"
    },
    {
      "arrival": "2014-05-09 10:31",
      "departure": "2014-05-09 10:31",
      "serviceId": "2_18",
      "tripId": "2_15026",
      "routeId": "2_0067",
      "headsign": "67 | Brécé"
    },
    {
      "arrival": "2014-05-09 11:31",
      "departure": "2014-05-09 11:31",
      "serviceId": "2_18",
      "tripId": "2_15016",
      "routeId": "2_0067",
      "headsign": "67 | Brécé"
    },
    {
      "arrival": "2014-05-09 12:27",
      "departure": "2014-05-09 12:27",
      "serviceId": "2_18",
      "tripId": "2_15086",
      "routeId": "2_0067",
      "headsign": "67 | Brécé"
    },
    {
      "arrival": "2014-05-09 12:57",
      "departure": "2014-05-09 12:57",
      "serviceId": "2_18",
      "tripId": "2_15091",
      "routeId": "2_0067",
      "headsign": "67 | Brécé"
    },
    {
      "arrival": "2014-05-09 13:37",
      "departure": "2014-05-09 13:37",
      "serviceId": "2_18",
      "tripId": "2_15096",
      "routeId": "2_0067",
      "headsign": "67 | Brécé"
    },
    {
      "arrival": "2014-05-09 14:32",
      "departure": "2014-05-09 14:32",
      "serviceId": "2_18",
      "tripId": "2_15101",
      "routeId": "2_0067",
      "headsign": "67 | Brécé"
    },
    {
      "arrival": "2014-05-09 15:32",
      "departure": "2014-05-09 15:32",
      "serviceId": "2_18",
      "tripId": "2_15106",
      "routeId": "2_0067",
      "headsign": "67 | Brécé"
    },
    {
      "arrival": "2014-05-09 16:27",
      "departure": "2014-05-09 16:27",
      "serviceId": "2_18",
      "tripId": "2_15111",
      "routeId": "2_0067",
      "headsign": "67 | Brécé"
    },
    {
      "arrival": "2014-05-09 17:08",
      "departure": "2014-05-09 17:08",
      "serviceId": "2_18",
      "tripId": "2_15081",
      "routeId": "2_0067",
      "headsign": "67 | Brécé"
    },
    {
      "arrival": "2014-05-09 17:34",
      "departure": "2014-05-09 17:34",
      "serviceId": "2_18",
      "tripId": "2_15121",
      "routeId": "2_0067",
      "headsign": "67 | Brécé"
    },
    {
      "arrival": "2014-05-09 18:15",
      "departure": "2014-05-09 18:15",
      "serviceId": "2_18",
      "tripId": "2_15131",
      "routeId": "2_0067",
      "headsign": "67 | Brécé"
    },
    {
      "arrival": "2014-05-09 18:35",
      "departure": "2014-05-09 18:35",
      "serviceId": "2_18",
      "tripId": "2_15136",
      "routeId": "2_0067",
      "headsign": "67 | Brécé"
    },
    {
      "arrival": "2014-05-09 18:54",
      "departure": "2014-05-09 18:54",
      "serviceId": "2_18",
      "tripId": "2_15146",
      "routeId": "2_0067",
      "headsign": "67 | Brécé"
    },
    {
      "arrival": "2014-05-09 19:32",
      "departure": "2014-05-09 19:32",
      "serviceId": "2_18",
      "tripId": "2_15151",
      "routeId": "2_0067",
      "headsign": "67 | Brécé"
    },
    {
      "arrival": "2014-05-09 19:51",
      "departure": "2014-05-09 19:51",
      "serviceId": "2_18",
      "tripId": "2_15156",
      "routeId": "2_0067",
      "headsign": "67 | Brécé"
    },
    {
      "arrival": "2014-05-09 20:10",
      "departure": "2014-05-09 20:10",
      "serviceId": "2_18",
      "tripId": "2_15161",
      "routeId": "2_0067",
      "headsign": "67 | Brécé"
    },
    {
      "arrival": "2014-05-09 20:39",
      "departure": "2014-05-09 20:39",
      "serviceId": "2_18",
      "tripId": "2_15166",
      "routeId": "2_0067",
      "headsign": "67 | Brécé"
    },
    {
      "arrival": "2014-05-09 21:07",
      "departure": "2014-05-09 21:07",
      "serviceId": "2_18",
      "tripId": "2_15171",
      "routeId": "2_0067",
      "headsign": "67 | Brécé"
    },
    {
      "arrival": "2014-05-10 00:31",
      "departure": "2014-05-10 00:31",
      "serviceId": "2_19",
      "tripId": "2_14394",
      "routeId": "2_0011",
      "headsign": "11 | Saint-Saëns Monniais Brécé"
    },
    {
      "arrival": "2014-05-10 02:06",
      "departure": "2014-05-10 02:06",
      "serviceId": "2_19",
      "tripId": "2_14392",
      "routeId": "2_0011",
      "headsign": "11 | Saint-Saëns Monniais Brécé"
    }
  ]
}