{
  "date": "2015-01-12 00:00",
  "stop": {
    "id": "2_2716",
    "lat": 48.0686191,
    "lon": -1.66595219,
    "name": "Petit Beaulieu",
    "code": 2716
  },
  "routes": [
    {
      "id": "2_0061",
      "textColor": "FFFFFF",
      "color": "E6396C",
      "description": "Métropolitaine",
      "longName": "Rennes (Henri Fréville) \u003c\u003e Noyal-Châtillon-sur-Seiche / Saint-Erblon",
      "shortName": "61",
      "type": 3,
      "agencyId": "2"
    }
  ],
  "stopTimes": [
    {
      "arrival": "2015-01-12 06:40",
      "departure": "2015-01-12 06:40",
      "serviceId": "2_16",
      "tripId": "2_6428",
      "routeId": "2_0061",
      "headsign": "61 | Noyal-Châtillon Saint-Erblon"
    },
    {
      "arrival": "2015-01-12 06:58",
      "departure": "2015-01-12 06:58",
      "serviceId": "2_16",
      "tripId": "2_6381",
      "routeId": "2_0061",
      "headsign": "61 | Noyal-Châtillon Saint-Erblon"
    },
    {
      "arrival": "2015-01-12 07:13",
      "departure": "2015-01-12 07:13",
      "serviceId": "2_16",
      "tripId": "2_6386",
      "routeId": "2_0061",
      "headsign": "61 | Noyal-Châtillon Saint-Erblon"
    },
    {
      "arrival": "2015-01-12 07:28",
      "departure": "2015-01-12 07:28",
      "serviceId": "2_16",
      "tripId": "2_6106",
      "routeId": "2_0061",
      "headsign": "61 | Noyal-Châtillon Saint-Erblon"
    },
    {
      "arrival": "2015-01-12 07:48",
      "departure": "2015-01-12 07:48",
      "serviceId": "2_16",
      "tripId": "2_6176",
      "routeId": "2_0061",
      "headsign": "61 | Noyal-Châtillon Saint-Erblon"
    },
    {
      "arrival": "2015-01-12 08:03",
      "departure": "2015-01-12 08:03",
      "serviceId": "2_16",
      "tripId": "2_6186",
      "routeId": "2_0061",
      "headsign": "61 | Noyal-Châtillon Saint-Erblon"
    },
    {
      "arrival": "2015-01-12 08:18",
      "departure": "2015-01-12 08:18",
      "serviceId": "2_16",
      "tripId": "2_6191",
      "routeId": "2_0061",
      "headsign": "61 | Noyal-Châtillon Saint-Erblon"
    },
    {
      "arrival": "2015-01-12 08:36",
      "departure": "2015-01-12 08:36",
      "serviceId": "2_16",
      "tripId": "2_6101",
      "routeId": "2_0061",
      "headsign": "61 | Noyal-Châtillon Saint-Erblon"
    },
    {
      "arrival": "2015-01-12 08:56",
      "departure": "2015-01-12 08:56",
      "serviceId": "2_16",
      "tripId": "2_6196",
      "routeId": "2_0061",
      "headsign": "61 | Noyal-Châtillon Saint-Erblon"
    },
    {
      "arrival": "2015-01-12 09:28",
      "departure": "2015-01-12 09:28",
      "serviceId": "2_16",
      "tripId": "2_6201",
      "routeId": "2_0061",
      "headsign": "61 | Noyal-Châtillon Saint-Erblon"
    },
    {
      "arrival": "2015-01-12 09:58",
      "departure": "2015-01-12 09:58",
      "serviceId": "2_16",
      "tripId": "2_6206",
      "routeId": "2_0061",
      "headsign": "61 | Noyal-Châtillon Saint-Erblon"
    },
    {
      "arrival": "2015-01-12 10:28",
      "departure": "2015-01-12 10:28",
      "serviceId": "2_16",
      "tripId": "2_6211",
      "routeId": "2_0061",
      "headsign": "61 | Noyal-Châtillon Saint-Erblon"
    },
    {
      "arrival": "2015-01-12 10:58",
      "departure": "2015-01-12 10:58",
      "serviceId": "2_16",
      "tripId": "2_6216",
      "routeId": "2_0061",
      "headsign": "61 | Noyal-Châtillon Saint-Erblon"
    },
    {
      "arrival": "2015-01-12 11:28",
      "departure": "2015-01-12 11:28",
      "serviceId": "2_16",
      "tripId": "2_6221",
      "routeId": "2_0061",
      "headsign": "61 | Noyal-Châtillon Saint-Erblon"
    },
    {
      "arrival": "2015-01-12 11:58",
      "departure": "2015-01-12 11:58",
      "serviceId": "2_16",
      "tripId": "2_6226",
      "routeId": "2_0061",
      "headsign": "61 | Noyal-Châtillon Saint-Erblon"
    },
    {
      "arrival": "2015-01-12 12:28",
      "departure": "2015-01-12 12:28",
      "serviceId": "2_16",
      "tripId": "2_6231",
      "routeId": "2_0061",
      "headsign": "61 | Noyal-Châtillon Saint-Erblon"
    },
    {
      "arrival": "2015-01-12 12:58",
      "departure": "2015-01-12 12:58",
      "serviceId": "2_16",
      "tripId": "2_6236",
      "routeId": "2_0061",
      "headsign": "61 | Noyal-Châtillon Saint-Erblon"
    },
    {
      "arrival": "2015-01-12 13:28",
      "departure": "2015-01-12 13:28",
      "serviceId": "2_16",
      "tripId": "2_6241",
      "routeId": "2_0061",
      "headsign": "61 | Noyal-Châtillon Saint-Erblon"
    },
    {
      "arrival": "2015-01-12 13:59",
      "departure": "2015-01-12 13:59",
      "serviceId": "2_16",
      "tripId": "2_6391",
      "routeId": "2_0061",
      "headsign": "61 | Noyal-Châtillon Saint-Erblon"
    },
    {
      "arrival": "2015-01-12 14:29",
      "departure": "2015-01-12 14:29",
      "serviceId": "2_16",
      "tripId": "2_6396",
      "routeId": "2_0061",
      "headsign": "61 | Noyal-Châtillon Saint-Erblon"
    },
    {
      "arrival": "2015-01-12 14:59",
      "departure": "2015-01-12 14:59",
      "serviceId": "2_16",
      "tripId": "2_6246",
      "routeId": "2_0061",
      "headsign": "61 | Noyal-Châtillon Saint-Erblon"
    },
    {
      "arrival": "2015-01-12 15:19",
      "departure": "2015-01-12 15:19",
      "serviceId": "2_16",
      "tripId": "2_6416",
      "routeId": "2_0061",
      "headsign": "61 | Noyal-Châtillon Saint-Erblon"
    },
    {
      "arrival": "2015-01-12 15:39",
      "departure": "2015-01-12 15:39",
      "serviceId": "2_16",
      "tripId": "2_6401",
      "routeId": "2_0061",
      "headsign": "61 | Noyal-Châtillon Saint-Erblon"
    },
    {
      "arrival": "2015-01-12 15:59",
      "departure": "2015-01-12 15:59",
      "serviceId": "2_16",
      "tripId": "2_6251",
      "routeId": "2_0061",
      "headsign": "61 | Noyal-Châtillon Saint-Erblon"
    },
    {
      "arrival": "2015-01-12 16:19",
      "departure": "2015-01-12 16:19",
      "serviceId": "2_16",
      "tripId": "2_6406",
      "routeId": "2_0061",
      "headsign": "61 | Noyal-Châtillon Saint-Erblon"
    },
    {
      "arrival": "2015-01-12 16:39",
      "departure": "2015-01-12 16:39",
      "serviceId": "2_16",
      "tripId": "2_6411",
      "routeId": "2_0061",
      "headsign": "61 | Noyal-Châtillon Saint-Erblon"
    },
    {
      "arrival": "2015-01-12 17:04",
      "departure": "2015-01-12 17:04",
      "serviceId": "2_16",
      "tripId": "2_6066",
      "routeId": "2_0061",
      "headsign": "61 | Noyal-Châtillon Saint-Erblon"
    },
    {
      "arrival": "2015-01-12 17:24",
      "departure": "2015-01-12 17:24",
      "serviceId": "2_16",
      "tripId": "2_6071",
      "routeId": "2_0061",
      "headsign": "61 | Noyal-Châtillon Saint-Erblon"
    },
    {
      "arrival": "2015-01-12 17:44",
      "departure": "2015-01-12 17:44",
      "serviceId": "2_16",
      "tripId": "2_6076",
      "routeId": "2_0061",
      "headsign": "61 | Noyal-Châtillon Saint-Erblon"
    },
    {
      "arrival": "2015-01-12 18:09",
      "departure": "2015-01-12 18:09",
      "serviceId": "2_16",
      "tripId": "2_6091",
      "routeId": "2_0061",
      "headsign": "61 | Noyal-Châtillon Saint-Erblon"
    },
    {
      "arrival": "2015-01-12 18:29",
      "departure": "2015-01-12 18:29",
      "serviceId": "2_16",
      "tripId": "2_6081",
      "routeId": "2_0061",
      "headsign": "61 | Noyal-Châtillon Saint-Erblon"
    },
    {
      "arrival": "2015-01-12 18:49",
      "departure": "2015-01-12 18:49",
      "serviceId": "2_16",
      "tripId": "2_6286",
      "routeId": "2_0061",
      "headsign": "61 | Noyal-Châtillon Saint-Erblon"
    },
    {
      "arrival": "2015-01-12 19:15",
      "departure": "2015-01-12 19:15",
      "serviceId": "2_16",
      "tripId": "2_6256",
      "routeId": "2_0061",
      "headsign": "61 | Noyal-Châtillon Saint-Erblon"
    },
    {
      "arrival": "2015-01-12 19:34",
      "departure": "2015-01-12 19:34",
      "serviceId": "2_16",
      "tripId": "2_6291",
      "routeId": "2_0061",
      "headsign": "61 | Noyal-Châtillon Saint-Erblon"
    },
    {
      "arrival": "2015-01-12 19:58",
      "departure": "2015-01-12 19:58",
      "serviceId": "2_16",
      "tripId": "2_6261",
      "routeId": "2_0061",
      "headsign": "61 | Noyal-Châtillon Saint-Erblon"
    },
    {
      "arrival": "2015-01-12 20:28",
      "departure": "2015-01-12 20:28",
      "serviceId": "2_16",
      "tripId": "2_6266",
      "routeId": "2_0061",
      "headsign": "61 | Noyal-Châtillon Saint-Erblon"
    },
    {
      "arrival": "2015-01-12 20:58",
      "departure": "2015-01-12 20:58",
      "serviceId": "2_16",
      "tripId": "2_6086",
      "routeId": "2_0061",
      "headsign": "61 | Noyal-Châtillon Saint-Erblon"
    }
  ]
}