{
  "headsign": "172 | Chartres-de-Bretagne",
  "stopTimes": [
    {
      "stop": {
        "id": "2_1534",
        "lat": 48.08831454,
        "lon": -1.67444337,
        "name": "Henri Fréville",
        "code": 1534
      },
      "arrival": 62100,
      "departure": 62100
    },
    {
      "stop": {
        "id": "2_2942",
        "lat": 48.04202435,
        "lon": -1.69612399,
        "name": "Collège Pôle Sud",
        "code": 2942
      },
      "arrival": 62880,
      "departure": 62880
    },
    {
      "stop": {
        "id": "2_2922",
        "lat": 48.03705289,
        "lon": -1.69713431,
        "name": "Vieux Bourg",
        "code": 2922
      },
      "arrival": 63000,
      "departure": 63000
    },
    {
      "stop": {
        "id": "2_2923",
        "lat": 48.03470268,
        "lon": -1.69977512,
        "name": "Cornouaille",
        "code": 2923
      },
      "arrival": 63060,
      "departure": 63060
    },
    {
      "stop": {
        "id": "2_2924",
        "lat": 48.03549509,
        "lon": -1.70610918,
        "name": "Argoat",
        "code": 2924
      },
      "arrival": 63120,
      "departure": 63120
    },
    {
      "stop": {
        "id": "2_2927",
        "lat": 48.03317189,
        "lon": -1.70739442,
        "name": "Parc de Loisirs",
        "code": 2927
      },
      "arrival": 63180,
      "departure": 63180
    }
  ],
  "route": {
    "id": "2_0172",
    "textColor": "3D3C3F",
    "color": "FFDD00",
    "description": "Express métropolitaine",
    "longName": "Rennes (Henri Fréville) \u003c\u003e Chartres-de-Bretagne / Pont-Péan",
    "shortName": "172",
    "type": 3,
    "agencyId": "2"
  }
}