{
  "date": "2015-03-30 00:00",
  "stop": {
    "id": "2_2908",
    "lat": 48.041413,
    "lon": -1.712515,
    "name": "Callouët",
    "code": 2908
  },
  "routes": [
    {
      "id": "2_0091",
      "textColor": "1A171B",
      "color": "AECC52",
      "description": "Intercommunale",
      "longName": "Bruz / Chartres \u003c\u003e Noyal-Châtillon-sur-Seiche",
      "shortName": "91",
      "type": 3,
      "agencyId": "2"
    }
  ],
  "stopTimes": [
    {
      "arrival": "2015-03-30 07:57",
      "departure": "2015-03-30 07:57",
      "serviceId": "2_16",
      "tripId": "2_22027",
      "routeId": "2_0091",
      "headsign": "91 | Bruz Cicé Blossac"
    },
    {
      "arrival": "2015-03-30 08:31",
      "departure": "2015-03-30 08:31",
      "serviceId": "2_16",
      "tripId": "2_22147",
      "routeId": "2_0091",
      "headsign": "91 | Bruz Pont-Réan"
    },
    {
      "arrival": "2015-03-30 09:01",
      "departure": "2015-03-30 09:01",
      "serviceId": "2_16",
      "tripId": "2_22017",
      "routeId": "2_0091",
      "headsign": "91 | Bruz Cicé Blossac"
    },
    {
      "arrival": "2015-03-30 09:52",
      "departure": "2015-03-30 09:52",
      "serviceId": "2_16",
      "tripId": "2_22112",
      "routeId": "2_0091",
      "headsign": "91 | Bruz Pont-Réan"
    },
    {
      "arrival": "2015-03-30 13:33",
      "departure": "2015-03-30 13:33",
      "serviceId": "2_16",
      "tripId": "2_22022",
      "routeId": "2_0091",
      "headsign": "91 | Bruz Pont-Réan"
    },
    {
      "arrival": "2015-03-30 14:18",
      "departure": "2015-03-30 14:18",
      "serviceId": "2_16",
      "tripId": "2_22037",
      "routeId": "2_0091",
      "headsign": "91 | Bruz Cicé Blossac"
    },
    {
      "arrival": "2015-03-30 15:03",
      "departure": "2015-03-30 15:03",
      "serviceId": "2_16",
      "tripId": "2_22087",
      "routeId": "2_0091",
      "headsign": "91 | Bruz Pont-Réan"
    },
    {
      "arrival": "2015-03-30 15:38",
      "departure": "2015-03-30 15:38",
      "serviceId": "2_16",
      "tripId": "2_22102",
      "routeId": "2_0091",
      "headsign": "91 | Bruz Cicé Blossac"
    },
    {
      "arrival": "2015-03-30 16:07",
      "departure": "2015-03-30 16:07",
      "serviceId": "2_16",
      "tripId": "2_22042",
      "routeId": "2_0091",
      "headsign": "91 | Bruz Pont-Réan"
    },
    {
      "arrival": "2015-03-30 16:37",
      "departure": "2015-03-30 16:37",
      "serviceId": "2_16",
      "tripId": "2_22152",
      "routeId": "2_0091",
      "headsign": "91 | Bruz Cicé Blossac"
    },
    {
      "arrival": "2015-03-30 17:05",
      "departure": "2015-03-30 17:05",
      "serviceId": "2_16",
      "tripId": "2_22047",
      "routeId": "2_0091",
      "headsign": "91 | Bruz Pont-Réan"
    },
    {
      "arrival": "2015-03-30 17:33",
      "departure": "2015-03-30 17:33",
      "serviceId": "2_16",
      "tripId": "2_22107",
      "routeId": "2_0091",
      "headsign": "91 | Bruz Cicé Blossac"
    },
    {
      "arrival": "2015-03-30 18:07",
      "departure": "2015-03-30 18:07",
      "serviceId": "2_16",
      "tripId": "2_22052",
      "routeId": "2_0091",
      "headsign": "91 | Bruz Pont-Réan"
    },
    {
      "arrival": "2015-03-30 18:32",
      "departure": "2015-03-30 18:32",
      "serviceId": "2_16",
      "tripId": "2_22157",
      "routeId": "2_0091",
      "headsign": "91 | Bruz Cicé Blossac"
    }
  ]
}